pyfileexplorer/__init__.py
pyfileexplorer/__main__.py
pyfileexplorer/app.py
pyfileexplorer/templates/index.html
hostlocal-1.0.0.dist-info/METADATA
hostlocal-1.0.0.dist-info/WHEEL
hostlocal-1.0.0.dist-info/entry_points.txt
hostlocal-1.0.0.dist-info/top_level.txt
hostlocal-1.0.0.dist-info/RECORD
